django_indices/__init__.py
django_indices/admin.py
django_indices/apps.py
django_indices/json.py
django_indices/models.py
django_indices/tests.py
django_indices/views.py
django_indices/management/__init__.py
django_indices/management/commands/__init__.py
django_indices/management/commands/migrate_indices.py
django_indices/migrations/0001_initial.py
django_indices/migrations/0002_index_where.py
django_indices/migrations/__init__.py
django_indices-0.0.4.post2.dist-info/LICENCE
django_indices-0.0.4.post2.dist-info/METADATA
django_indices-0.0.4.post2.dist-info/WHEEL
django_indices-0.0.4.post2.dist-info/top_level.txt
django_indices-0.0.4.post2.dist-info/RECORD
