Metadata-Version: 2.1
Name: django-indices
Version: 0.0.4.post2
Summary: Create JSON indexes concurrently
Home-page: https://github.com/jatinderjit/django-indices
Author: Jatinderjit Singh
Author-email: jatinderjit89@gmail.com
License: UNKNOWN
Platform: UNKNOWN
Classifier: Framework :: Django
Classifier: Programming Language :: Python :: 3
Classifier: Programming Language :: Python :: 3.6
Classifier: Programming Language :: Python :: 3.7
Classifier: Programming Language :: Python :: 3.8
Classifier: License :: OSI Approved :: MIT License
Classifier: Operating System :: OS Independent
